<?xml version='1.0' encoding='UTF-8'?>
<addons>
  <addon id="plugin.video.sticky" name="Sticky Nnnnnn" provider-name="Sticky" version="1.0.1_nnnnnn">
    <requires>
      <import addon="xbmc.python" version="4.0.0" />
    </requires>
    <extension library="default.py" point="xbmc.python.pluginsource" provides="video">
      <provides>video</provides>
    </extension>
    <extension library="default.py" point="xbmc.addon.metadata">
      <summary>Sticky Nnnnnn 1.0.1</summary>
      <description>Sticky Nnnnnn 1.0.1</description>
      <provides>video</provides>
      <platform>all</platform>
    </extension>
  </addon>
  <addon id="plugin.video.sticky" name="Sticky Nnnnnn" provider-name="Sticky" version="1.0.2_nnnnnn">
    <requires>
      <import addon="xbmc.python" version="4.0.0" />
    </requires>
    <extension library="default.py" point="xbmc.python.pluginsource" provides="video">
      <provides>video</provides>
    </extension>
    <extension library="default.py" point="xbmc.addon.metadata">
      <summary>Sticky Nnnnnn 1.0.2</summary>
      <description>Sticky Nnnnnn 1.0.2</description>
      <provides>video</provides>
      <platform>all</platform>
    </extension>
  </addon>
</addons>